econometric_causality/__init__.py
econometric_causality/module.py
econometric_causality-0.0.2.dist-info/LICENSE
econometric_causality-0.0.2.dist-info/METADATA
econometric_causality-0.0.2.dist-info/WHEEL
econometric_causality-0.0.2.dist-info/top_level.txt
econometric_causality-0.0.2.dist-info/RECORD
